jackptoke_de_toolkit/__init__.py
jackptoke_de_toolkit/main.py
jackptoke_de_toolkit/vm.py
jackptoke_de_toolkit-0.1.0.dist-info/METADATA
jackptoke_de_toolkit-0.1.0.dist-info/WHEEL
jackptoke_de_toolkit-0.1.0.dist-info/entry_points.txt
jackptoke_de_toolkit-0.1.0.dist-info/RECORD
