Metadata-Version: 2.3
Name: jackptoke-de-toolkit
Version: 0.1.0
Summary: 
Author: Jack Toke
Author-email: jackptoke@gmail.com
Requires-Python: >=3.12
Classifier: Programming Language :: Python :: 3
Classifier: Programming Language :: Python :: 3.12
Classifier: Programming Language :: Python :: 3.13
Requires-Dist: click (>=8.1.8,<9.0.0)
Requires-Dist: google-cloud-compute (>=1.26.0,<2.0.0)
